PyUtilToolKit/__init__.py
PyUtilToolKit/util_log.py
personalizedutilitykits-1.0.6.dist-info/METADATA
personalizedutilitykits-1.0.6.dist-info/WHEEL
personalizedutilitykits-1.0.6.dist-info/top_level.txt
personalizedutilitykits-1.0.6.dist-info/RECORD
